simpleencrypt/__init__.py
simpleencrypt/aes256.py
simpleencrypt-1.0.6.dist-info/METADATA
simpleencrypt-1.0.6.dist-info/WHEEL
simpleencrypt-1.0.6.dist-info/top_level.txt
simpleencrypt-1.0.6.dist-info/RECORD
