Metadata-Version: 2.1
Name: simpleencrypt
Version: 1.0.6
Summary: SimpleEncrypt is a Cross-Language Encryption Library
Home-page: UNKNOWN
Author: Shreyas Nayak
Author-email: <shreyasnayak21@gmail.com>
License: UNKNOWN
Keywords: Encryption,Cross-Language Encryption
Platform: UNKNOWN
Classifier: Development Status :: 4 - Beta
Classifier: Intended Audience :: Developers
Classifier: Programming Language :: Python :: 3
Classifier: Operating System :: Unix
